{
  "task_id": "lesson-python-gbk-encoding-error",
  "title": "Python GBK 编码错误 — Windows/WSL 跨平台",
  "domain": "devops",
  "tags": [
    "python",
    "encoding",
    "gbk",
    "windows",
    "wsl"
  ],
  "problem": "在 WSL 中运行 Python 脚本，读取或写入文件时报：\n\n或 Cron 日志中出现乱码。",
  "solution": "```python\n# 1. 读取文件时显式指定编码\nwith open(\"file.txt\", \"r\", encoding=\"utf-8\") as f:\n    content = f.read()\n\n# 2. 写入文件时指定编码\nwith open(\"file.txt\", \"w\", encoding=\"utf-8\") as f:\n    f.write(content)\n\n# 3. 设置环境变量（推荐永久）\n# 在 ~/.bashrc 中添加：\nexport PYTHONIOENCODING=utf-8\nexport LANG=C.UTF-8\n\n# 4. 对系统日志\nsudo locale-gen zh_CN.UTF-8\n```",
  "source": "lessons/contrib/python-gbk-encoding-error.md",
  "test_cmd": ""
}